odoo10_addon_crm_lead_website-10.0.1.0.0-py2.7-nspkg.pth
odoo/addons/crm_lead_website/README.rst
odoo/addons/crm_lead_website/__init__.py
odoo/addons/crm_lead_website/__manifest__.py
odoo/addons/crm_lead_website/i18n/ar.po
odoo/addons/crm_lead_website/i18n/bg.po
odoo/addons/crm_lead_website/i18n/bs.po
odoo/addons/crm_lead_website/i18n/ca.po
odoo/addons/crm_lead_website/i18n/cs.po
odoo/addons/crm_lead_website/i18n/da.po
odoo/addons/crm_lead_website/i18n/de.po
odoo/addons/crm_lead_website/i18n/el_GR.po
odoo/addons/crm_lead_website/i18n/en_GB.po
odoo/addons/crm_lead_website/i18n/es.po
odoo/addons/crm_lead_website/i18n/es_AR.po
odoo/addons/crm_lead_website/i18n/es_CL.po
odoo/addons/crm_lead_website/i18n/es_CO.po
odoo/addons/crm_lead_website/i18n/es_CR.po
odoo/addons/crm_lead_website/i18n/es_DO.po
odoo/addons/crm_lead_website/i18n/es_EC.po
odoo/addons/crm_lead_website/i18n/es_MX.po
odoo/addons/crm_lead_website/i18n/es_PE.po
odoo/addons/crm_lead_website/i18n/et.po
odoo/addons/crm_lead_website/i18n/eu.po
odoo/addons/crm_lead_website/i18n/fa.po
odoo/addons/crm_lead_website/i18n/fi.po
odoo/addons/crm_lead_website/i18n/fr.po
odoo/addons/crm_lead_website/i18n/gl.po
odoo/addons/crm_lead_website/i18n/he.po
odoo/addons/crm_lead_website/i18n/hr.po
odoo/addons/crm_lead_website/i18n/hr_HR.po
odoo/addons/crm_lead_website/i18n/hu.po
odoo/addons/crm_lead_website/i18n/id.po
odoo/addons/crm_lead_website/i18n/it.po
odoo/addons/crm_lead_website/i18n/ja.po
odoo/addons/crm_lead_website/i18n/ko.po
odoo/addons/crm_lead_website/i18n/lt.po
odoo/addons/crm_lead_website/i18n/lv.po
odoo/addons/crm_lead_website/i18n/mk.po
odoo/addons/crm_lead_website/i18n/mn.po
odoo/addons/crm_lead_website/i18n/nb.po
odoo/addons/crm_lead_website/i18n/nl.po
odoo/addons/crm_lead_website/i18n/pl.po
odoo/addons/crm_lead_website/i18n/pt_BR.po
odoo/addons/crm_lead_website/i18n/ru.po
odoo/addons/crm_lead_website/i18n/sk.po
odoo/addons/crm_lead_website/i18n/sl.po
odoo10_addon_crm_lead_website-10.0.1.0.0.dist-info/DESCRIPTION.rst
odoo10_addon_crm_lead_website-10.0.1.0.0.dist-info/METADATA
odoo10_addon_crm_lead_website-10.0.1.0.0.dist-info/RECORD
odoo10_addon_crm_lead_website-10.0.1.0.0.dist-info/WHEEL
odoo10_addon_crm_lead_website-10.0.1.0.0.dist-info/metadata.json
odoo10_addon_crm_lead_website-10.0.1.0.0.dist-info/namespace_packages.txt
odoo10_addon_crm_lead_website-10.0.1.0.0.dist-info/top_level.txt
